libdiscid/__init__.py
libdiscid/_discid.cp39-win32.pyd
libdiscid/_discid.pyi
libdiscid/exceptions.py
libdiscid/py.typed
libdiscid/compat/__init__.py
libdiscid/compat/discid.py
libdiscid/tests/__init__.py
libdiscid/tests/common.py
libdiscid/tests/test_compat_discid.py
libdiscid/tests/test_libdiscid.py
python_libdiscid-2.0.3.dist-info/LICENSE
python_libdiscid-2.0.3.dist-info/METADATA
python_libdiscid-2.0.3.dist-info/WHEEL
python_libdiscid-2.0.3.dist-info/top_level.txt
python_libdiscid-2.0.3.dist-info/RECORD
