Metadata-Version: 2.1
Name: python-libdiscid
Version: 2.0.3
Summary: Python bindings for libdiscid
Home-page: https://github.com/sebastinas/python-libdiscid
Author: Sebastian Ramacher
Author-email: sebastian@ramacher.at
License: MIT
Classifier: Development Status :: 5 - Production/Stable
Classifier: Intended Audience :: Developers
Classifier: License :: OSI Approved :: MIT License
Classifier: Operating System :: OS Independent
Classifier: Programming Language :: Python :: 3
Classifier: Topic :: Multimedia :: Sound/Audio :: CD Audio :: CD Ripping
Classifier: Topic :: Software Development :: Libraries :: Python Modules
Requires-Python: >=3.8
License-File: LICENSE
